ts_demo_lib/__init__.py
ts_demo_lib/_nbdev.py
ts_demo_lib/core.py
ts_demo_lib/ts_demo.py
ts_demo_lib-0.0.12.dist-info/LICENSE
ts_demo_lib-0.0.12.dist-info/METADATA
ts_demo_lib-0.0.12.dist-info/WHEEL
ts_demo_lib-0.0.12.dist-info/entry_points.txt
ts_demo_lib-0.0.12.dist-info/top_level.txt
ts_demo_lib-0.0.12.dist-info/RECORD
