Metadata-Version: 2.1
Name: ts-demo-lib
Version: 0.0.12
Summary: T science demo libary
Home-page: https://github.com/nkhuyu-msft/ts_demo
Author: YH
Author-email: yuhu@microsoft.com
License: Apache Software License 2.0
Keywords: Demo
Platform: UNKNOWN
Classifier: Development Status :: 3 - Alpha
Classifier: Intended Audience :: Developers
Classifier: License :: OSI Approved :: Apache Software License
Classifier: Natural Language :: English
Classifier: Programming Language :: Python :: 3.6
Classifier: Programming Language :: Python :: 3.7
Classifier: Programming Language :: Python :: 3.8
Requires-Python: >=3.6
